generalindex/Authenticator.py
generalindex/DatalakeHandler.py
generalindex/GxApi.py
generalindex/HTTPCaller.py
generalindex/StatusHandler.py
generalindex/TaskHandler.py
generalindex/Timeseries.py
generalindex/__init__.py
generalindex/constants.py
generalindex/exceptions.py
generalindex/utils.py
generalindex-0.2.6.dist-info/licenses/LICENSE
generalindex-0.2.6.dist-info/METADATA
generalindex-0.2.6.dist-info/WHEEL
generalindex-0.2.6.dist-info/top_level.txt
generalindex-0.2.6.dist-info/RECORD
