Metadata-Version: 2.4
Name: generalindex
Version: 0.2.6
Summary: Python SDK for the General Index platform
Home-page: https://www.general-index.com/
Author: General Index
Author-email: info@general-index.com
Classifier: Programming Language :: Python :: 3
Classifier: License :: OSI Approved :: MIT License
Classifier: Operating System :: OS Independent
Requires-Python: >=3.9
License-File: LICENSE
Requires-Dist: requests~=2.31.0
Requires-Dist: urllib3~=2.0.7
Requires-Dist: deprecated~=1.2.14
Requires-Dist: setuptools~=69.0.1
Requires-Dist: pytz~=2022.7.1
Dynamic: author
Dynamic: author-email
Dynamic: classifier
Dynamic: description
Dynamic: description-content-type
Dynamic: home-page
Dynamic: license-file
Dynamic: requires-dist
Dynamic: requires-python
Dynamic: summary
